<?xml version="1.0" encoding="UTF-8"?>
<metadata xml:lang="en"><Esri><CreaDate>20201201</CreaDate><CreaTime>06261000</CreaTime><ArcGISFormat>1.0</ArcGISFormat><SyncOnce>TRUE</SyncOnce><ModDate>20210514</ModDate><ModTime>061334</ModTime></Esri><toolbox name="GeoAI-Tools" alias="GeoAI-Tools"><arcToolboxHelpPath>c:\program files\arcgis\pro\Resources\Help\gp</arcToolboxHelpPath><toolsets/></toolbox><dataIdInfo><idCitation><resTitle>GeoAI-Tools</resTitle></idCitation></dataIdInfo><distInfo><distributor><distorFormat><formatName>ArcToolbox Toolbox</formatName></distorFormat></distributor></distInfo></metadata>
